mybudgeter/__init__.py
mybudgeter/database/__init__.py
mybudgeter/database/budget.py
mybudgeter/database/database.py
mybudgeter/database/transactions.py
mybudgeter/utilities/__init__.py
mybudgeter/utilities/helper.py
mybudgeter/utilities/users.py
mybudgeter-0.0.3.dist-info/LICENSE
mybudgeter-0.0.3.dist-info/METADATA
mybudgeter-0.0.3.dist-info/WHEEL
mybudgeter-0.0.3.dist-info/top_level.txt
mybudgeter-0.0.3.dist-info/RECORD
