Metadata-Version: 2.1
Name: mybudgeter
Version: 0.0.3
Summary: A Python package to create simple household budgets.
Author: Kyle Deng, Jacob Rosen
Project-URL: Homepage, https://github.com/kt1720/Data-533-Group-16-project
Classifier: Programming Language :: Python :: 3
Classifier: License :: OSI Approved :: MIT License
Classifier: Operating System :: OS Independent
Requires-Python: >=3.9
License-File: LICENSE
